setup.cfg
setup.py
duplines/__init__.py
duplines/cli.py
duplines.egg-info/PKG-INFO
duplines.egg-info/SOURCES.txt
duplines.egg-info/dependency_links.txt
duplines.egg-info/entry_points.txt
duplines.egg-info/not-zip-safe
duplines.egg-info/requires.txt
duplines.egg-info/top_level.txt