Metadata-Version: 1.1
Name: duplines
Version: 0.1.0
Summary: duplines cli eliminates duplicate lines in a file and keeps the sorting order
Home-page: https://github.com/altipard/duplines
Author: Daniel Altiparmak
Author-email: daniel.altiparmak@googlemail.com
License: BSD
Platform: any
Classifier: Development Status :: 4 - Beta
Classifier: Environment :: Console
Classifier: Intended Audience :: Developers
Classifier: License :: OSI Approved :: BSD License
Classifier: Operating System :: POSIX
Classifier: Operating System :: MacOS
Classifier: Operating System :: Unix
Classifier: Operating System :: Microsoft :: Windows
Classifier: Programming Language :: Python
Classifier: Programming Language :: Python :: 2
Classifier: Programming Language :: Python :: 3
Classifier: Topic :: Software Development :: Libraries :: Python Modules
